graphility/__init__.py
graphility/database.py
graphility/database_gevent.py
graphility/database_safe_shared.py
graphility/database_super_thread_safe.py
graphility/database_thread_safe.py
graphility/debug_stuff.py
graphility/env.py
graphility/hash_index.py
graphility/index.py
graphility/indexcreator.py
graphility/lfu_cache.py
graphility/lfu_cache_with_lock.py
graphility/migrate.py
graphility/misc.py
graphility/patch.py
graphility/rr_cache.py
graphility/rr_cache_with_lock.py
graphility/sharded_hash.py
graphility/sharded_index.py
graphility/storage.py
graphility/tree_index.py
graphility-0.0.1.dist-info/LICENSE
graphility-0.0.1.dist-info/WHEEL
graphility-0.0.1.dist-info/METADATA
graphility-0.0.1.dist-info/RECORD
