Metadata-Version: 2.1
Name: graphility
Version: 0.0.1
Summary: Pure-python NoSQL database.
Home-page: https://github.com/Gromobrody/graphility
License: Apache-2.0
Keywords: database,nosql
Author: Dominik Kozaczko
Author-email: dominik@kozaczko.info
Requires-Python: >=3.8,<4.0
Classifier: Development Status :: 2 - Pre-Alpha
Classifier: Intended Audience :: Developers
Classifier: License :: OSI Approved :: Apache Software License
Classifier: Operating System :: OS Independent
Classifier: Programming Language :: Python :: 3
Classifier: Programming Language :: Python :: 3.8
Classifier: Programming Language :: Python :: 3.9
Classifier: Topic :: Database
Classifier: Topic :: Database :: Database Engines/Servers
Classifier: Topic :: Internet
Classifier: Topic :: Software Development
Project-URL: Repository, https://github.com/Gromobrody/graphility
